blankimage/__init__.py
blankimage/format_options.py
blankimage/parse_cli_options.py
blankimage/process_task.py
blankimage-0.1.2.dist-info/METADATA
blankimage-0.1.2.dist-info/WHEEL
blankimage-0.1.2.dist-info/entry_points.txt
blankimage-0.1.2.dist-info/RECORD
